huff/__init__.py
huff/config.py
huff/gistools.py
huff/goodness_of_fit.py
huff/helper.py
huff/models.py
huff/ors.py
huff/osm.py
huff/tests/__init__.py
huff/tests/tests_huff.py
huff/tests/data/Haslach.cpg
huff/tests/data/Haslach.dbf
huff/tests/data/Haslach.prj
huff/tests/data/Haslach.qmd
huff/tests/data/Haslach.shp
huff/tests/data/Haslach.shx
huff/tests/data/Haslach_new_supermarket.cpg
huff/tests/data/Haslach_new_supermarket.dbf
huff/tests/data/Haslach_new_supermarket.prj
huff/tests/data/Haslach_new_supermarket.qmd
huff/tests/data/Haslach_new_supermarket.shp
huff/tests/data/Haslach_new_supermarket.shx
huff/tests/data/Haslach_supermarkets.cpg
huff/tests/data/Haslach_supermarkets.dbf
huff/tests/data/Haslach_supermarkets.prj
huff/tests/data/Haslach_supermarkets.qmd
huff/tests/data/Haslach_supermarkets.shp
huff/tests/data/Haslach_supermarkets.shx
huff/tests/data/Wieland2015.xlsx
huff-1.6.8.dist-info/METADATA
huff-1.6.8.dist-info/WHEEL
huff-1.6.8.dist-info/top_level.txt
huff-1.6.8.dist-info/RECORD
