Metadata-Version: 2.4
Name: huff
Version: 1.6.8
Summary: huff: Huff Model Market Area Analysis
Author: Thomas Wieland
Author-email: geowieland@googlemail.com
Requires-Dist: geopandas
Requires-Dist: pandas
Requires-Dist: numpy
Requires-Dist: statsmodels==0.14.2
Requires-Dist: scipy==1.15.3
Requires-Dist: shapely
Requires-Dist: requests
Requires-Dist: matplotlib
Requires-Dist: pillow
Requires-Dist: contextily
Requires-Dist: openpyxl
Dynamic: author
Dynamic: author-email
Dynamic: description
Dynamic: description-content-type
Dynamic: requires-dist
Dynamic: summary
